README.rst
hammock.py
setup.py
hammock.egg-info/PKG-INFO
hammock.egg-info/SOURCES.txt
hammock.egg-info/dependency_links.txt
hammock.egg-info/requires.txt
hammock.egg-info/top_level.txt