Metadata-Version: 1.0
Name: hammock
Version: 0.2.4
Summary: rest like a boss
Home-page: https://github.com/kadirpekel/hammock
Author: Kadir Pekel
Author-email: kadirpekel@gmail.com
License: UNKNOWN
Platform: UNKNOWN
